configuraptor/__about__.py
configuraptor/__init__.py
configuraptor/abs.py
configuraptor/alias.py
configuraptor/beautify.py
configuraptor/binary_config.py
configuraptor/cls.py
configuraptor/core.py
configuraptor/dump.py
configuraptor/errors.py
configuraptor/helpers.py
configuraptor/postpone.py
configuraptor/py.typed
configuraptor/singleton.py
configuraptor/type_converters.py
configuraptor/loaders/__init__.py
configuraptor/loaders/_types.py
configuraptor/loaders/loaders_shared.py
configuraptor/loaders/py.typed
configuraptor/loaders/register.py
configuraptor-1.28.2.dist-info/METADATA
configuraptor-1.28.2.dist-info/WHEEL
configuraptor-1.28.2.dist-info/licenses/LICENSE.txt
configuraptor-1.28.2.dist-info/RECORD
