Metadata-Version: 2.4
Name: configuraptor
Version: 1.28.2
Summary: Load toml/yaml/json config files into classes for a typed config (type hinting etc.)
Project-URL: Documentation, https://github.com/trialandsuccess/configuraptor#readme
Project-URL: Issues, https://github.com/trialandsuccess/configuraptor/issues
Project-URL: Source, https://github.com/trialandsuccess/configuraptor
Author-email: Robin van der Noord <robin@trialandsuccess.nl>
License-Expression: MIT
License-File: LICENSE.txt
Classifier: Development Status :: 4 - Beta
Classifier: Programming Language :: Python
Classifier: Programming Language :: Python :: 3.11
Classifier: Programming Language :: Python :: 3.12
Classifier: Programming Language :: Python :: 3.13
Classifier: Programming Language :: Python :: 3.14
Classifier: Programming Language :: Python :: Implementation :: CPython
Classifier: Programming Language :: Python :: Implementation :: PyPy
Requires-Python: >=3.10
Requires-Dist: python-dotenv
Requires-Dist: pyyaml
Requires-Dist: requests
Requires-Dist: tomli
Requires-Dist: tomli-w
Requires-Dist: typeguard>=4.0
Requires-Dist: typing-extensions
Provides-Extra: dev
Requires-Dist: hatch; extra == 'dev'
Requires-Dist: pytest-mypy-testing; extra == 'dev'
Requires-Dist: su6[all]; extra == 'dev'
Requires-Dist: types-pyyaml; extra == 'dev'
Requires-Dist: types-requests; extra == 'dev'
Requires-Dist: xmltodict; extra == 'dev'
